prober/__init__.py
prober/prober.py
prober-0.1.1.dist-info/METADATA
prober-0.1.1.dist-info/WHEEL
prober-0.1.1.dist-info/entry_points.txt
prober-0.1.1.dist-info/top_level.txt
prober-0.1.1.dist-info/RECORD
