Metadata-Version: 2.1
Name: prober
Version: 0.1.1
Summary: Software bugs predictor based on machine learning techniques
Home-page: https://github.com/slxiao/prober
Author: slxiao
Author-email: shliangxiao@gmail.com
License: MIT
Platform: UNKNOWN
Classifier: Intended Audience :: Developers
Classifier: Natural Language :: English
Classifier: License :: OSI Approved :: BSD License
Classifier: Operating System :: OS Independent
Classifier: Programming Language :: Python
Classifier: Programming Language :: Python :: 2
Classifier: Programming Language :: Python :: 2.7
Classifier: Programming Language :: Python :: 3
Classifier: Programming Language :: Python :: 3.6
Classifier: Programming Language :: Python :: 3.7
Classifier: Topic :: Software Development :: Libraries :: Python Modules
Requires-Python: >=2.6, !=3.0.*, !=3.1.*, !=3.2.*, <4
